cfaf/__init__.py
cfaf/create_folder_and_files.py
cfaf-0.1.dist-info/METADATA
cfaf-0.1.dist-info/WHEEL
cfaf-0.1.dist-info/entry_points.txt
cfaf-0.1.dist-info/top_level.txt
cfaf-0.1.dist-info/RECORD
