Metadata-Version: 2.1
Name: cfaf
Version: 0.1
Summary: A package to create folders and files
Home-page: http://example.com/cfaf
Author: waleedoff
Author-email: waled988@hotmail.com
